CHANGELOG.txt
LICENSE.txt
MANIFEST.in
README.txt
setup.py
libmorse/__init__.py
libmorse.egg-info/PKG-INFO
libmorse.egg-info/SOURCES.txt
libmorse.egg-info/dependency_links.txt
libmorse.egg-info/top_level.txt