Metadata-Version: 1.1
Name: libmorse
Version: 0.0.1
Summary: A text util library
Home-page: https://github.com/shahprog/textils/
Author: Md Shahriyar Alam
Author-email: mdshahriyaralam552@gmail.com
License: MIT
Keywords: morsify,morse code,demorse,decode morse
Platform: UNKNOWN
Classifier: Development Status :: 5 - Production/Stable
Classifier: Intended Audience :: Education
Classifier: Operating System :: POSIX :: Linux
Classifier: Operating System :: Microsoft :: Windows
Classifier: Operating System :: MacOS
Classifier: License :: OSI Approved :: MIT License
Classifier: Programming Language :: Python :: 3
